Metadata-Version: 2.1
Name: godspeedio
Version: 0.1.2
Summary: memory efficient, fast, and easy to use stream processing library
Home-page: https://github.com/apburton84/godspeed
Author: Anthony Burton
Author-email: apburton84@gmail.com
License: MIT
Download-URL: https://codeload.github.com/apburton84/godspeed/zip/refs/heads/main
Keywords: STREAM,PROCESSING,MEMORY,EFFICIENT,FAST,EASY,USE,LIBRARY
Platform: UNKNOWN
Classifier: Development Status :: 5 - Production/Stable
Classifier: Intended Audience :: Developers
Classifier: Topic :: Software Development :: Libraries :: Python Modules
Classifier: License :: OSI Approved :: MIT License
Classifier: Programming Language :: Python :: 3.9
Classifier: Programming Language :: Python :: 3.10
Classifier: Programming Language :: Python :: 3.11
Classifier: Operating System :: OS Independent
Classifier: Natural Language :: English
Classifier: Typing :: Typed
License-File: LICENSE.txt
